sparg/__init__.py
sparg/dispersal.py
sparg/importance_sample.py
sparg/locate.py
sparg/relate.py
sparg/trees.py
sparg/utils.py
sparg-1.0.1.dist-info/LICENSE
sparg-1.0.1.dist-info/METADATA
sparg-1.0.1.dist-info/WHEEL
sparg-1.0.1.dist-info/top_level.txt
sparg-1.0.1.dist-info/RECORD
