Metadata-Version: 2.1
Name: sparg
Version: 1.0.1
Summary: A package to estimate dispersal rates and locate genetic ancestors from tree sequences
Home-page: https://github.com/mmosmond/sparg
Author: Matthew Osmond
Author-email: mm.osmond@utoronto.ca
License: UNKNOWN
Project-URL: Bug Tracker, https://github.com/mmosmond/sparg/issues
Project-URL: Tutorial, https://github.com/mmosmond/sparg/tutorial/tutorial.ipynb
Platform: UNKNOWN
Classifier: Programming Language :: Python :: 3
Classifier: License :: OSI Approved :: GNU General Public License v3 or later (GPLv3+)
Classifier: Operating System :: OS Independent
Requires-Python: >=3.7
License-File: LICENSE
Requires-Dist: numpy
Requires-Dist: scipy
Requires-Dist: dendropy
Requires-Dist: tskit
Requires-Dist: tqdm
